cassandra_dev_sync/__init__.py
cassandra_dev_sync/cli.py
cassandra_dev_sync-0.1.2.dist-info/METADATA
cassandra_dev_sync-0.1.2.dist-info/WHEEL
cassandra_dev_sync-0.1.2.dist-info/entry_points.txt
cassandra_dev_sync-0.1.2.dist-info/RECORD
