Metadata-Version: 2.1
Name: cassandra-dev-sync
Version: 0.1.2
Summary: 
Author: omri fima
Author-email: of@a.com
Requires-Python: >=3.9,<4.0
Classifier: Programming Language :: Python :: 3
Classifier: Programming Language :: Python :: 3.9
Classifier: Programming Language :: Python :: 3.10
Classifier: Programming Language :: Python :: 3.11
Classifier: Programming Language :: Python :: 3.12
Requires-Dist: cassandra-driver (>=3.29.1,<4.0.0)
Requires-Dist: click (>=8.1.7,<9.0.0)
Requires-Dist: pyyaml (>=6.0.2,<7.0.0)
Requires-Dist: setuptools (>=72.2.0,<73.0.0)
Requires-Dist: tqdm (>=4.66.5,<5.0.0)
